CHANGES.txt
MANIFEST.in
README.rst
setup.py
update_c.sh
mdr/__init__.py
mdr/_tree.c
mdr/_tree.pyx
mdr/mdr.py
mdr/tree.py
mdr/utils.py
mdr.egg-info/PKG-INFO
mdr.egg-info/SOURCES.txt
mdr.egg-info/dependency_links.txt
mdr.egg-info/requires.txt
mdr.egg-info/top_level.txt