Metadata-Version: 1.0
Name: mdr
Version: 0.0.1
Summary: python library to detect and extract listing data from HTML page
Home-page: https://github.com/tpeng/mdr
Author: Terry Peng
Author-email: pengtaoo@gmail.com
License: MIT
Platform: UNKNOWN
